mypack228/__init__.py
mypack228-0.0.1.dist-info/METADATA
mypack228-0.0.1.dist-info/WHEEL
mypack228-0.0.1.dist-info/top_level.txt
mypack228-0.0.1.dist-info/RECORD
