Metadata-Version: 2.4
Name: mypack228
Version: 0.0.1
Summary: A minimal Python package that prints hello world for testing purposes
Author-email: Your Name <you@example.com>
License: MIT
Requires-Python: >=3.7
